[{"title":"Reloj Deportivo","description":"Reloj runner.","price":100,"thumbnail":[],"code":"14322","stock":25,"category":"accesorios","status":true},
{"title":"Gorra","description":"Gorra Running","price":550,"thumbnail":"","code":"54322","stock":5,"category":"accesorios","status":true},
{"title":"Short Deportivo","description":"Short negro adiddas","price":1300,"thumbnail":[],"code":"54325","stock":20,"category":"Ropa deportiva","status":true},
{"title":"Pantalon","description":"Verde Chupin","price":"255","thumbnail":[],"code":"441","stock":"2","category":"Ropa de vestir","status":true},
{"title":"Remera","description":"Remera negra manga corta","price":"155","thumbnail":[],"code":"741","stock":"25","category":"Ropa de vestir","status":true},
{"title":"Buzo","description":"Buzo de abrigo de lana verde","price":"955","thumbnail":[],"code":"211","stock":"10","category":"Ropa de vestir","status":true},
{"title":"Remera","description":"Manga Larga roja","price":"55","thumbnail":[],"code":"212","stock":"5","category":"Ropa de vestir","status":true},
{"title":"Campera","description":"Campera de abrigo negra","price":"1855","thumbnail":[],"code":"251","stock":"10","category":"Ropa de abrigo","status":true},
{"title":"Zapatos","description":"Zapatos Chupin","price":"1655","thumbnail":[],"code":"041","stock":"20","category":"Calzado de vestir","status":true},
{"title":"Zapatos","description":"Zapatos de charol","price":"1650","thumbnail":[],"code":"042","stock":"21","category":"Calzado de vestir","status":true},
{"title":"Zapatos","description":"Zapatos Borsego","price":"2655","thumbnail":[],"code":"040","stock":"20","category":"Calzado","status":true},
{"title":"Zapatos","description":"Zapatos Militares","price":"2655","thumbnail":[],"code":"090","stock":"20","category":"Calzado","status":true},
{"title":"Pantalon","description":"Jean Azul","price":"290","thumbnail":[],"code":"644","stock":"20","category":"Ropa de vestir","status":true},
{"title":"Pantalon","description":"Jean verde","price":"290","thumbnail":[],"code":"645","stock":"28","category":"Ropa de vestir","status":true},
{"title":"Remera","description":"Remera runner","price":"1250","thumbnail":[],"code":"007","stock":"50","category":"Ropa deportiva","status":true},
{"title":"Remera","description":"Remera de futbol","price":"3250","thumbnail":[],"code":"017","stock":"30","category":"Ropa deportiva","status":true},
{"title":"Remera","description":"Remera térmica","price":"1050","thumbnail":[],"code":"005","stock":"10","category":"Ropa deportiva","status":true},
{"title":"Pantalón","description":"Pantalón térmico","price":"1350","thumbnail":[],"code":"001","stock":"10","category":"Ropa deportiva","status":true}]